{
    "status": true,
    "data": {
        "id": "g87gsdf7g6sd89fg67sd8fg4s65dgsdgf",
        "parent": "3g26jkh4562gj234523k4j523",
        "published": true,
        "html": "<div class=\"quote-component\"><figure></figure><p class=\"quote-component__text\">Consectetur ipsum in deserunt anim Lorem sit ullamco. Deserunt ipsum sunt id nisi nisi et ullamco consequat eu et deserunt. Velit amet incididunt eiusmod est elit minim veniam pariatur aliqua esse eu. Ea et ut ex occaecat incididunt ullamco aliqua dolore anim velit. Quis consectetur nisi sunt commodo dolor aliqua qui labore veniam duis. Laborum excepteur aliqua aute excepteur occaecat sint sunt tempor deserunt do.</p><p class=\"quote-component__title\">Est aute elit sint<br /><small>Voluptate commodo</small></p></div>",
        "type": "quote"
    }
}